tuxtrigger/__init__.py
tuxtrigger/__main__.py
tuxtrigger/argparser.py
tuxtrigger/configparser.py
tuxtrigger/constants.py
tuxtrigger/exceptions.py
tuxtrigger/inputvalidation.py
tuxtrigger/manifest.py
tuxtrigger/repository.py
tuxtrigger/request.py
tuxtrigger/storage.py
tuxtrigger/tuxintegration.py
tuxtrigger/utils.py
tuxtrigger/yamlload.py
tuxtrigger-0.9.0.dist-info/entry_points.txt
tuxtrigger-0.9.0.dist-info/LICENSE
tuxtrigger-0.9.0.dist-info/WHEEL
tuxtrigger-0.9.0.dist-info/METADATA
tuxtrigger-0.9.0.dist-info/RECORD
