Metadata-Version: 2.1
Name: tuxtrigger
Version: 0.9.0
Summary: TuxTrigger Project by Linaro
Home-page: https://tuxsuite.com/
Author: Pawel Szymaszek
Author-email: pawel.szymaszek@linaro.org
Requires-Python: >=3.6
Classifier: License :: OSI Approved :: MIT License
Requires-Dist: tuxsuite
Requires-Dist: squad-client
Requires-Dist: jinja2
Requires-Dist: requests
Requires-Dist: PyYAML
